<?xml version="1.0" encoding="utf-8"?>
<Toc Version="2" MINORVERSION="0">
	<Application>
		<Class Name="Os">
			<File Name="arsimproxy.dll" HashValue="B6831EEF7E96FEBDBE334ED0A550E515" ProjectDependent="1"/>
			<File Name="BRLcReg.dll" HashValue="5CE306FC22306CD6BCD7E40C2D6CC31F" ProjectDependent="1"/>
			<File Name="InaFrms.dll" HashValue="BCBB8AB4B7168E2BB538CF86E5B742A3" ProjectDependent="1"/>
			<Folder Name="Brm">
				<File Name="@cfAR000.br" HashValue="4B942ACD39E18D205AB83DBB501D52B7" ProjectDependent="1"/>
				<File Name="@sbAR000.br" HashValue="AA4BF7D1D236CDE82EAE8FF2F1FA6E6A" ProjectDependent="1"/>
			</Folder>
			<Folder Name="System">
				<Folder Name="BASE">
					<Folder Name="COMPONENTS">
						<File Name="ArLcTextP.br" HashValue="99D06CA804FC1F2BF22B3DC37B896F23" ProjectDependent="1"/>
						<File Name="unitsys.br" HashValue="89CA005A80005CAE78ACC113FBD49928" ProjectDependent="1"/>
					</Folder>
					<Folder Name="HWD">
						<File Name="AsHwdhw_upl.xml.gz" HashValue="D9E8CF0207F671D1672BBFC18D43F705" ProjectDependent="1"/>
						<File Name="AsHwdSimulation.xml.gz" HashValue="F0716C58B5B7E0AE53FF026C91A948B3" ProjectDependent="1"/>
					</Folder>
				</Folder>
				<Folder Name="SDM">
					<File Name="arsdm.tar.gz" HashValue="3160A9FE8441CA16FC847DDB704B25B3" ProjectDependent="1"/>
				</Folder>
				<Folder Name="TOC">
					<File Name="ftoc.xml" HashValue="F83AEC703141D083AB19580424BF781A" ProjectDependent="1"/>
				</Folder>
				<Folder Name="WEBSERV">
					<File Name="webserv.br" HashValue="22706D96EBA07AF42826F75EAD9FA250" ProjectDependent="1"/>
				</Folder>
			</Folder>
		</Class>
	</Application>
</Toc>